setup.py
anybox/__init__.py
anybox.scripts.odoo.egg-info/PKG-INFO
anybox.scripts.odoo.egg-info/SOURCES.txt
anybox.scripts.odoo.egg-info/dependency_links.txt
anybox.scripts.odoo.egg-info/entry_points.txt
anybox.scripts.odoo.egg-info/namespace_packages.txt
anybox.scripts.odoo.egg-info/not-zip-safe
anybox.scripts.odoo.egg-info/requires.txt
anybox.scripts.odoo.egg-info/top_level.txt
anybox/scripts/__init__.py
anybox/scripts/odoo/__init__.py
anybox/scripts/odoo/import_csv.py