Metadata-Version: 1.0
Name: anybox.scripts.odoo
Version: 0.1.0
Summary: Import CSV Odoo scripts
Home-page: UNKNOWN
Author: Jean-SÃ©bastien Suzanne
Author-email: jssuzanne@anybox.fr
License: UNKNOWN
Platform: UNKNOWN
